datagen_protocol/__version__.py
datagen_protocol/config.py
datagen_protocol/migrations/__init__.py
datagen_protocol/migrations/datapoint_migrations/__init__.py
datagen_protocol/migrations/datapoint_migrations/migration_1_0.py
datagen_protocol/migrations/migration_base.py
datagen_protocol/migrations/migration_runner.py
datagen_protocol/migrations/sequence_migrations/__init__.py
datagen_protocol/resources/defaults.toml
datagen_protocol/resources/documentation.toml
datagen_protocol/resources/expression_presets/expression_presets.json
datagen_protocol/schema/__init__.py
datagen_protocol/schema/attributes.py
datagen_protocol/schema/base.py
datagen_protocol/schema/d3.py
datagen_protocol/schema/environment/__init__.py
datagen_protocol/schema/environment/background.py
datagen_protocol/schema/environment/camera.py
datagen_protocol/schema/environment/light.py
datagen_protocol/schema/fields.py
datagen_protocol/schema/hic/__init__.py
datagen_protocol/schema/hic/sequence.py
datagen_protocol/schema/humans/__init__.py
datagen_protocol/schema/humans/accessories.py
datagen_protocol/schema/humans/expressions/__init__.py
datagen_protocol/schema/humans/expressions/expression.py
datagen_protocol/schema/humans/expressions/presets.py
datagen_protocol/schema/humans/human.py
datagen_protocol/schema/request.py
utils/__init__.py
utils/logging.py
datagen_protocol_core-0.36.0.dist-info/METADATA
datagen_protocol_core-0.36.0.dist-info/WHEEL
datagen_protocol_core-0.36.0.dist-info/RECORD
