Metadata-Version: 2.1
Name: datagen-protocol-core
Version: 0.36.0
Summary: Datagen Protocol Core
Author: ShayZ
Author-email: shay.zilberman@datagen.tech
Requires-Python: >=3.8,<4.0
Classifier: Programming Language :: Python :: 3
Classifier: Programming Language :: Python :: 3.8
Classifier: Programming Language :: Python :: 3.9
Classifier: Programming Language :: Python :: 3.10
Classifier: Programming Language :: Python :: 3.11
Requires-Dist: dynaconf (==2.2.3)
Requires-Dist: pydantic
